reverseshellgenerator/__init__.py
reverseshellgenerator/generator.py
reverseshellgenerator/shells_templates.py
tests/__init__.py
tests/test_generator.py
revshell_generator-1.0.12.dist-info/LICENSE
revshell_generator-1.0.12.dist-info/METADATA
revshell_generator-1.0.12.dist-info/WHEEL
revshell_generator-1.0.12.dist-info/entry_points.txt
revshell_generator-1.0.12.dist-info/top_level.txt
revshell_generator-1.0.12.dist-info/RECORD
