Metadata-Version: 2.1
Name: revshell-generator
Version: 1.0.12
Summary: Reverse shell commands generator
Home-page: https://github.com/totekuh/reverse-shell-generator
Author: totekuh
Author-email: totekuh@protonmail.com
Project-URL: Bug Reports, https://github.com/totekuh/reverse-shell-generator/issues
Project-URL: Source, https://github.com/totekuh/reverse-shell-generator
Keywords: pentest,red-team,shell
Classifier: Development Status :: 5 - Production/Stable
Classifier: Environment :: Console
Classifier: Intended Audience :: Information Technology
Classifier: Intended Audience :: Other Audience
Classifier: License :: OSI Approved :: MIT License
Classifier: Operating System :: POSIX :: Linux
Classifier: Operating System :: Microsoft :: Windows
Classifier: Programming Language :: Python :: 3
Classifier: Programming Language :: Python :: 3.6
Classifier: Programming Language :: Python :: 3.7
Classifier: Programming Language :: Python :: 3.8
Classifier: Programming Language :: Python :: 3.9
Classifier: Programming Language :: Python :: 3 :: Only
Requires-Python: >=3.6, <4
License-File: LICENSE
Requires-Dist: termcolor
Requires-Dist: netifaces
